context/__init__.py
pycontext_lib-1.0.2.dist-info/LICENSE
pycontext_lib-1.0.2.dist-info/METADATA
pycontext_lib-1.0.2.dist-info/WHEEL
pycontext_lib-1.0.2.dist-info/entry_points.txt
pycontext_lib-1.0.2.dist-info/top_level.txt
pycontext_lib-1.0.2.dist-info/RECORD
