Metadata-Version: 2.1
Name: pycontext-lib
Version: 1.0.2
Summary: Lots of properties that help with program context!
Author-email: Carl Furtado <carlzfurtado@gmail.com>
License: The MIT License (MIT)
Project-URL: Homepage, https://github.com/User0332/pycontext
Keywords: context,properties
Classifier: License :: OSI Approved :: MIT License
Classifier: Programming Language :: Python
Classifier: Programming Language :: Python :: 3
Classifier: Operating System :: OS Independent
Requires-Python: >=3.9
License-File: LICENSE
